pysank/__init__.py
pysank/cli.py
pysank/pysank.py
pysank-0.1.12.dist-info/AUTHORS.rst
pysank-0.1.12.dist-info/LICENSE
pysank-0.1.12.dist-info/METADATA
pysank-0.1.12.dist-info/WHEEL
pysank-0.1.12.dist-info/entry_points.txt
pysank-0.1.12.dist-info/top_level.txt
pysank-0.1.12.dist-info/RECORD
