Metadata-Version: 2.1
Name: pysank
Version: 0.1.12
Summary: personal utility file for data science
Home-page: https://github.com/msank00/pysank
Author: Sankarshan Mridha
Author-email: sankarshan7@gmail.com
License: MIT license
Keywords: pysank
Platform: UNKNOWN
Classifier: Development Status :: 2 - Pre-Alpha
Classifier: Intended Audience :: Developers
Classifier: License :: OSI Approved :: MIT License
Classifier: Natural Language :: English
Classifier: Programming Language :: Python :: 2
Classifier: Programming Language :: Python :: 2.7
Classifier: Programming Language :: Python :: 3
Classifier: Programming Language :: Python :: 3.4
Classifier: Programming Language :: Python :: 3.5
Classifier: Programming Language :: Python :: 3.6
Classifier: Programming Language :: Python :: 3.7
Requires-Dist: Click (>=6.0)
